{
  "type": "Feature",
  "geometry": {
    "type": "Polygon",
    "coordinates": [
      [
        [
          135.84349141200005,
          -0.7661502829999449
        ],
        [
          135.84083396500012,
          -0.7687128259999554
        ],
        [
          135.8383700380001,
          -0.7663896939999404
        ],
        [
          135.8301014110001,
          -0.7590133649999302
        ],
        [
          135.82772195000007,
          -0.7565149309999697
        ],
        [
          135.82730548100005,
          -0.755872429999954
        ],
        [
          135.84349141200005,
          -0.7661502829999449
        ]
      ]
    ]
  },
  "properties": {
    "kode": "91.06.21.2002"
  }
}